{
  "unpublishedPage": {
    "name": "Market",
    "slug": "market",
    "layouts": [
      {
        "viewMode": false,
        "dsl": {
          "widgetName": "MainContainer",
          "backgroundColor": "none",
          "rightColumn": 1174,
          "snapColumns": 64,
          "detachFromLayout": true,
          "widgetId": "0",
          "topRow": 0,
          "bottomRow": 830,
          "containerStyle": "none",
          "snapRows": 125,
          "parentRowSpace": 1,
          "type": "CANVAS_WIDGET",
          "canExtend": true,
          "version": 89,
          "minHeight": 890,
          "parentColumnSpace": 1,
          "dynamicTriggerPathList": [],
          "dynamicBindingPathList": [],
          "leftColumn": 0
        },
        "layoutOnLoadActions": [
          [
            {
              "id": "Market_LocationList",
              "name": "LocationList",
              "confirmBeforeExecute": false,
              "pluginType": "DB",
              "jsonPathKeys": [],
              "timeoutInMillisecond": 10000
            },
            {
              "id": "Market_Manager",
              "name": "Manager",
              "confirmBeforeExecute": false,
              "pluginType": "DB",
              "jsonPathKeys": [],
              "timeoutInMillisecond": 10000
            },
            {
              "id": "Market_ManagerALL",
              "name": "ManagerALL",
              "confirmBeforeExecute": false,
              "pluginType": "DB",
              "jsonPathKeys": [],
              "timeoutInMillisecond": 10000
            },
            {
              "id": "Market_MonthOptions",
              "name": "MonthOptions",
              "confirmBeforeExecute": false,
              "pluginType": "DB",
              "jsonPathKeys": [],
              "timeoutInMillisecond": 10000
            },
            {
              "id": "Market_SelectQuery",
              "name": "SelectQuery",
              "confirmBeforeExecute": false,
              "pluginType": "DB",
              "jsonPathKeys": [
                "JSONForm1.formData.LocationFilter",
                "JSONForm1.formData.MonthFilter"
              ],
              "timeoutInMillisecond": 10000
            }
          ]
        ],
        "layoutOnLoadActionErrors": [],
        "validOnPageLoadActions": true,
        "id": "Market",
        "deleted": false,
        "policies": [],
        "userPermissions": []
      }
    ],
    "userPermissions": [],
    "policies": [],
    "isHidden": false
  },
  "deleted": false,
  "gitSyncId": "66686f979c5dbf7c4bbe04c4_1cf6002d-73b9-42ae-a0d2-133a098f6ef8"
}